aws_decorators/__init__.py
aws_decorators-0.0.9.dist-info/DESCRIPTION.rst
aws_decorators-0.0.9.dist-info/METADATA
aws_decorators-0.0.9.dist-info/RECORD
aws_decorators-0.0.9.dist-info/WHEEL
aws_decorators-0.0.9.dist-info/metadata.json
aws_decorators-0.0.9.dist-info/top_level.txt
