Metadata-Version: 2.0
Name: aws-decorators
Version: 0.0.9
Summary: decorators for aws things
Home-page: https://github.com/devstuff-io/aws-decorators
Author: meganlkm
Author-email: devstuff.io@gmail.com
License: MIT
Keywords: aws,decorators
Platform: UNKNOWN
Classifier: Development Status :: 4 - Beta
Classifier: Intended Audience :: Developers
Classifier: License :: OSI Approved :: MIT License
Classifier: Programming Language :: Python
Classifier: Topic :: System :: Software Distribution
Classifier: Topic :: Utilities
Requires-Dist: boto3 (<=2.0.0,>=1.4.3)
